raster_loader/__init__.py
raster_loader/_version.py
raster_loader/cli/__init__.py
raster_loader/cli/bigquery.py
raster_loader/cli/databricks.py
raster_loader/cli/info.py
raster_loader/cli/snowflake.py
raster_loader/io/__init__.py
raster_loader/io/bigquery.py
raster_loader/io/common.py
raster_loader/io/databricks.py
raster_loader/io/datawarehouse.py
raster_loader/io/snowflake.py
raster_loader/lib/__init__.py
raster_loader/lib/errors.py
raster_loader/lib/geo.py
raster_loader/lib/utils.py
raster_loader/lib/valuelabels.py
raster_loader/tests/__init__.py
raster_loader/tests/mocks.py
raster_loader/tests/test_utils.py
raster_loader/tests/bigquery/__init__.py
raster_loader/tests/bigquery/test_cli.py
raster_loader/tests/bigquery/test_io.py
raster_loader/tests/databricks/__init__.py
raster_loader/tests/databricks/test_cli.py
raster_loader/tests/databricks/test_io.py
raster_loader/tests/snowflake/__init__.py
raster_loader/tests/snowflake/test_cli.py
raster_loader/tests/snowflake/test_io.py
raster_loader-0.11.3.dist-info/licenses/LICENSE
raster_loader-0.11.3.dist-info/METADATA
raster_loader-0.11.3.dist-info/WHEEL
raster_loader-0.11.3.dist-info/entry_points.txt
raster_loader-0.11.3.dist-info/top_level.txt
raster_loader-0.11.3.dist-info/RECORD
