Metadata-Version: 2.4
Name: raster-loader
Version: 0.11.3
Summary: Python library for loading GIS raster data to standard cloud-based data warehouses that don't natively support raster data.
Home-page: https://github.com/cartodb/raster-loader
Author: CARTO
License: BSD 3-Clause
Keywords: carto,raster,gis,data warehouse,bigquery,snowflake,databricks
Classifier: Development Status :: 5 - Production/Stable
Classifier: Intended Audience :: Developers
Classifier: License :: OSI Approved :: BSD License
Classifier: Natural Language :: English
Classifier: Programming Language :: Python :: 3
Classifier: Programming Language :: Python :: 3.9
Classifier: Programming Language :: Python :: 3.10
Classifier: Programming Language :: Python :: 3.11
Classifier: Programming Language :: Python :: 3.12
Requires-Python: >=3.9
License-File: LICENSE
Requires-Dist: click-plugins>=1.1.1
Requires-Dist: click>=8.1.3
Requires-Dist: db-dtypes>=1.0.5
Requires-Dist: pandas>=1.3.4
Requires-Dist: pyarrow>=10.0.1
Requires-Dist: pyproj>=3.2.1
Requires-Dist: rasterio>=1.3a3
Requires-Dist: rio-cogeo>=3.5.0
Requires-Dist: shapely>=1.7.1
Requires-Dist: quadbin>=0.2.0
Requires-Dist: tqdm>=4.64.1
Provides-Extra: test
Requires-Dist: pytest>=7.1.2; extra == "test"
Requires-Dist: pytest-mock>=3.8.2; extra == "test"
Requires-Dist: pytest-cov>=3.0.0; extra == "test"
Provides-Extra: bigquery
Requires-Dist: google-cloud-bigquery>=3.13.0; extra == "bigquery"
Requires-Dist: google-auth>=2.28.0; extra == "bigquery"
Provides-Extra: snowflake
Requires-Dist: snowflake-connector-python>=2.6.0; extra == "snowflake"
Provides-Extra: databricks
Provides-Extra: all
Requires-Dist: google-cloud-bigquery>=3.13.0; extra == "all"
Requires-Dist: google-auth>=2.28.0; extra == "all"
Requires-Dist: snowflake-connector-python>=2.6.0; extra == "all"
Dynamic: license-file
